mammos_mumag/__init__.py
mammos_mumag/cli.py
mammos_mumag/hysteresis.py
mammos_mumag/materials.py
mammos_mumag/mesh.py
mammos_mumag/parameters.py
mammos_mumag/py.typed
mammos_mumag/simulation.py
mammos_mumag/tofly.py
mammos_mumag/tools.py
mammos_mumag/mesh/README.json
mammos_mumag/mesh/cube20_singlegrain_msize2.fly
mammos_mumag/scripts/check.py
mammos_mumag/scripts/converters.py
mammos_mumag/scripts/energies.py
mammos_mumag/scripts/escript_tools.py
mammos_mumag/scripts/exani.py
mammos_mumag/scripts/external.py
mammos_mumag/scripts/hmag.py
mammos_mumag/scripts/jax_tools.py
mammos_mumag/scripts/loop.py
mammos_mumag/scripts/magnetization.py
mammos_mumag/scripts/mapping.py
mammos_mumag/scripts/materials.py
mammos_mumag/scripts/matrix.py
mammos_mumag/scripts/mesh.py
mammos_mumag/scripts/minimizers.py
mammos_mumag/scripts/solvers.py
mammos_mumag/scripts/store.py
mammos_mumag/scripts/tools.py
mammos_mumag/scripts/trafo.py
mammos_mumag/templates/krn.jinja
mammos_mumag/templates/p2.jinja
mammos_mumag-0.10.1.dist-info/METADATA
mammos_mumag-0.10.1.dist-info/WHEEL
mammos_mumag-0.10.1.dist-info/entry_points.txt
mammos_mumag-0.10.1.dist-info/licenses/LICENSE
mammos_mumag-0.10.1.dist-info/RECORD
