Metadata-Version: 2.4
Name: mammos-mumag
Version: 0.10.1
Summary: Finite element micromagnetic simulation tool.
Project-URL: Homepage, https://mammos-project.github.io
Project-URL: Documentation, https://mammos-project.github.io/mammos
Project-URL: Repository, https://github.com/MaMMoS-project/mammos-mumag
Project-URL: Issues, https://github.com/MaMMoS-project/mammos-mumag/issues
Project-URL: Changelog, https://mammos-project.github.io/mammos/changelog
Author: Thomas Schrefl, Swapneel Amit Pathak, Andrea Petrocchi, Samuel Holt, Martin Lang, Hans Fangohr
License-Expression: MIT
License-File: LICENSE
Classifier: Intended Audience :: Developers
Classifier: Intended Audience :: Education
Classifier: Intended Audience :: Science/Research
Classifier: Programming Language :: Python :: 3 :: Only
Classifier: Topic :: Scientific/Engineering :: Physics
Requires-Python: >=3.11
Requires-Dist: jax
Requires-Dist: jinja2>=3.1.6
Requires-Dist: mammos-entity>=0.10.0
Requires-Dist: mammos-units
Requires-Dist: matplotlib
Requires-Dist: numpy
Requires-Dist: pandas
Requires-Dist: psutil>=7
Requires-Dist: pydantic>=2.11
Requires-Dist: pyvista[all]
Requires-Dist: pyyaml>6
Requires-Dist: requests
Requires-Dist: scipy
Requires-Dist: tqdm
Requires-Dist: urllib3
Provides-Extra: cuda
Requires-Dist: jax[cuda]; extra == 'cuda'
Provides-Extra: examples
Requires-Dist: jupyterlab>3; extra == 'examples'
Requires-Dist: mammos-analysis>=0.1.4; extra == 'examples'
Requires-Dist: mammos-dft>=0.3.2; extra == 'examples'
Requires-Dist: mammos-spindynamics>=0.2.3; extra == 'examples'
Requires-Dist: nbval; extra == 'examples'
Provides-Extra: rocm
Requires-Dist: jax[rocm]; extra == 'rocm'
